Sequentiality/__init__.py
Sequentiality/sequentiality.py
sequentiality-0.0.2.dist-info/LICENSE
sequentiality-0.0.2.dist-info/METADATA
sequentiality-0.0.2.dist-info/WHEEL
sequentiality-0.0.2.dist-info/top_level.txt
sequentiality-0.0.2.dist-info/RECORD
