Metadata-Version: 2.1
Name: sequentiality
Version: 0.0.2
Summary: Extracts basic "Longest Consecutive Subsequences" features from a list of integers
Home-page: https://github.com/karaposu/sequentiality
Author: Enes
Author-email: enesesvetkuzucu@gmail.com
Project-URL: Bug Tracker, https://github.com/karaposu/sequentiality/issues
Classifier: Programming Language :: Python :: 3
Classifier: License :: OSI Approved :: MIT License
Classifier: Operating System :: OS Independent
Requires-Python: >=3.6
License-File: LICENSE
